jyinit/__init__.py
jyinit/__main__.py
jyinit/data/licenses.json
jyinit/data/templates.json
jyinit-0.0.8.dist-info/licenses/LICENSE
jyinit-0.0.8.dist-info/METADATA
jyinit-0.0.8.dist-info/WHEEL
jyinit-0.0.8.dist-info/entry_points.txt
jyinit-0.0.8.dist-info/top_level.txt
jyinit-0.0.8.dist-info/RECORD
