Metadata-Version: 2.4
Name: jyinit
Version: 0.0.8
Summary: jyinit - scaffold Python projects (CLI)
Author-email: Jeevan N <njeevan2216@gmail.com>
License: MIT
Project-URL: Homepage, https://njeevan.vercel.app/jyinit
Project-URL: Documentation, https://njeevan.vercel.app/jyinit-docs
Project-URL: Source, https://github.com/nj2216/jyinit
Project-URL: Issues, https://github.com/nj2216/jyinit/issues
Project-URL: ORG: SSSIHL, https://www.sssihl.edu.in/
Keywords: scaffold,cookiecutter,cli,python
Classifier: Programming Language :: Python :: 3
Classifier: License :: OSI Approved :: MIT License
Classifier: Operating System :: OS Independent
License-File: LICENSE
Requires-Dist: rich
Dynamic: license-file
